my_api_pkg/my_api_pkg.py
my_api_pkg-0.1.dist-info/METADATA
my_api_pkg-0.1.dist-info/WHEEL
my_api_pkg-0.1.dist-info/top_level.txt
my_api_pkg-0.1.dist-info/RECORD
